Workbook

Sheet Month
A1: OrderID | B1: Date | C1: Region | D1: SalesPerson | E1: Product | F1: Category | G1: Units | H1: UnitPrice | I1: Discount% | J1: PaymentMode | L1: Total Sales | M1: High Value Orders | N1: Discount Categorization | O1: Month | P1: Helper Column
A2: O001 | B2: 2026-01-01 | C2: North | D2: Asha | E2: Laptop | F2: Electronics | G2: 2 | H2: 50000 | I2: 10 | J2: Credit Card | L2: =Table1[[#This Row],[Units]]*Table1[[#This Row],[UnitPrice]]*(1-Table1[[#This Row],[Discount%]]/100) -> 90000 | M2: =IF(L2>50000,"High Value Order","") -> High Value Order | N2: {=_xlfn.IFS(Table1[[#This Row],[Discount%]]>10,"High Discount",Table1[[#This Row],[Discount%]]>5,"Medium Discount",Table1[[#This Row],[Discount%]]<=5,"Low Discount")} -> Medium Discount | O2: =TEXT(Table1[[#This Row],[Date]],"mmm") -> Jan | P2: =Table1[[#This Row],[OrderID]]&" "&Table1[[#This Row],[SalesPerson]] -> O001 Asha
A3: O002 | B3: 2026-01-02 | C3: South | D3: Rahul | E3: Phone | F3: Electronics | G3: 3 | H3: 20000 | I3: 5 | J3: UPI | L3: =Table1[[#This Row],[Units]]*Table1[[#This Row],[UnitPrice]]*(1-Table1[[#This Row],[Discount%]]/100) -> 57000 | M3: =IF(L3>50000,"High Value Order","") -> High Value Order | N3: {=_xlfn.IFS(Table1[[#This Row],[Discount%]]>10,"High Discount",Table1[[#This Row],[Discount%]]>5,"Medium Discount",Table1[[#This Row],[Discount%]]<=5,"Low Discount")} -> Low Discount | O3: =TEXT(Table1[[#This Row],[Date]],"mmm") -> Jan | P3: =Table1[[#This Row],[OrderID]]&" "&Table1[[#This Row],[SalesPerson]] -> O002 Rahul
A4: O003 | B4: 2026-01-03 | C4: East | D4: Neha | E4: Tablet | F4: Electronics | G4: 1 | H4: 30000 | I4: 0 | J4: Cash | L4: =Table1[[#This Row],[Units]]*Table1[[#This Row],[UnitPrice]]*(1-Table1[[#This Row],[Discount%]]/100) -> 30000 | M4: =IF(L4>50000,"High Value Order","") | N4: {=_xlfn.IFS(Table1[[#This Row],[Discount%]]>10,"High Discount",Table1[[#This Row],[Discount%]]>5,"Medium Discount",Table1[[#This Row],[Discount%]]<=5,"Low Discount")} -> Low Discount | O4: =TEXT(Table1[[#This Row],[Date]],"mmm") -> Jan | P4: =Table1[[#This Row],[OrderID]]&" "&Table1[[#This Row],[SalesPerson]] -> O003 Neha
A5: O004 | B5: 2026-01-04 | C5: West | D5: Vikram | E5: Headphones | F5: Electronics | G5: 5 | H5: 2000 | I5: 15 | J5: Debit Card | L5: =Table1[[#This Row],[Units]]*Table1[[#This Row],[UnitPrice]]*(1-Table1[[#This Row],[Discount%]]/100) -> 8500 | M5: =IF(L5>50000,"High Value Order","") | N5: {=_xlfn.IFS(Table1[[#This Row],[Discount%]]>10,"High Discount",Table1[[#This Row],[Discount%]]>5,"Medium Discount",Table1[[#This Row],[Discount%]]<=5,"Low Discount")} -> High Discount | O5: =TEXT(Table1[[#This Row],[Date]],"mmm") -> Jan | P5: =Table1[[#This Row],[OrderID]]&" "&Table1[[#This Row],[SalesPerson]] -> O004 Vikram
A6: O005 | B6: 2026-01-05 | C6: Central | D6: Priya | E6: Keyboard | F6: Electronics | G6: 4 | H6: 1500 | I6: 10 | J6: UPI | L6: =Table1[[#This Row],[Units]]*Table1[[#This Row],[UnitPrice]]*(1-Table1[[#This Row],[Discount%]]/100) -> 5400 | M6: =IF(L6>50000,"High Value Order","") | N6: {=_xlfn.IFS(Table1[[#This Row],[Discount%]]>10,"High Discount",Table1[[#This Row],[Discount%]]>5,"Medium Discount",Table1[[#This Row],[Discount%]]<=5,"Low Discount")} -> Medium Discount | O6: =TEXT(Table1[[#This Row],[Date]],"mmm") -> Jan | P6: =Table1[[#This Row],[OrderID]]&" "&Table1[[#This Row],[SalesPerson]] -> O005 Priya
A7: O006 | B7: 2026-01-06 | C7: North | D7: Asha | E7: Phone | F7: Electronics | G7: 2 | H7: 20000 | I7: 5 | J7: Credit Card | L7: =Table1[[#This Row],[Units]]*Table1[[#This Row],[UnitPrice]]*(1-Table1[[#This Row],[Discount%]]/100) -> 38000 | M7: =IF(L7>50000,"High Value Order","") | N7: {=_xlfn.IFS(Table1[[#This Row],[Discount%]]>10,"High Discount",Table1[[#This Row],[Discount%]]>5,"Medium Discount",Table1[[#This Row],[Discount%]]<=5,"Low Discount")} -> Low Discount | O7: =TEXT(Table1[[#This Row],[Date]],"mmm") -> Jan | P7: =Table1[[#This Row],[OrderID]]&" "&Table1[[#This Row],[SalesPerson]] -> O006 Asha
A8: O007 | B8: 2026-01-07 | C8: South | D8: Rahul | E8: Laptop | F8: Electronics | G8: 1 | H8: 50000 | I8: 0 | J8: UPI | L8: =Table1[[#This Row],[Units]]*Table1[[#This Row],[UnitPrice]]*(1-Table1[[#This Row],[Discount%]]/100) -> 50000 | M8: =IF(L8>50000,"High Value Order","") | N8: {=_xlfn.IFS(Table1[[#This Row],[Discount%]]>10,"High Discount",Table1[[#This Row],[Discount%]]>5,"Medium Discount",Table1[[#This Row],[Discount%]]<=5,"Low Discount")} -> Low Discount | O8: =TEXT(Table1[[#This Row],[Date]],"mmm") -> Jan | P8: =Table1[[#This Row],[OrderID]]&" "&Table1[[#This Row],[SalesPerson]] -> O007 Rahul
A9: O008 | B9: 2026-01-08 | C9: East | D9: Neha | E9: Keyboard | F9: Electronics | G9: 6 | H9: 1500 | I9: 10 | J9: Cash | L9: =Table1[[#This Row],[Units]]*Table1[[#This Row],[UnitPrice]]*(1-Table1[[#This Row],[Discount%]]/100) -> 8100 | M9: =IF(L9>50000,"High Value Order","") | N9: {=_xlfn.IFS(Table1[[#This Row],[Discount%]]>10,"High Discount",Table1[[#This Row],[Discount%]]>5,"Medium Discount",Table1[[#This Row],[Discount%]]<=5,"Low Discount")} -> Medium Discount | O9: =TEXT(Table1[[#This Row],[Date]],"mmm") -> Jan | P9: =Table1[[#This Row],[OrderID]]&" "&Table1[[#This Row],[SalesPerson]] -> O008 Neha
A10: O009 | B10: 2026-01-09 | C10: West | D10: Vikram | E10: Tablet | F10: Electronics | G10: 2 | H10: 30000 | I10: 5 | J10: Debit Card | L10: =Table1[[#This Row],[Units]]*Table1[[#This Row],[UnitPrice]]*(1-Table1[[#This Row],[Discount%]]/100) -> 57000 | M10: =IF(L10>50000,"High Value Order","") -> High Value Order | N10: {=_xlfn.IFS(Table1[[#This Row],[Discount%]]>10,"High Discount",Table1[[#This Row],[Discount%]]>5,"Medium Discount",Table1[[#This Row],[Discount%]]<=5,"Low Discount")} -> Low Discount | O10: =TEXT(Table1[[#This Row],[Date]],"mmm") -> Jan | P10: =Table1[[#This Row],[OrderID]]&" "&Table1[[#This Row],[SalesPerson]] -> O009 Vikram
A11: O010 | B11: 2026-01-10 | C11: Central | D11: Priya | E11: Headphones | F11: Electronics | G11: 8 | H11: 2000 | I11: 15 | J11: UPI | L11: =Table1[[#This Row],[Units]]*Table1[[#This Row],[UnitPrice]]*(1-Table1[[#This Row],[Discount%]]/100) -> 13600 | M11: =IF(L11>50000,"High Value Order","") | N11: {=_xlfn.IFS(Table1[[#This Row],[Discount%]]>10,"High Discount",Table1[[#This Row],[Discount%]]>5,"Medium Discount",Table1[[#This Row],[Discount%]]<=5,"Low Discount")} -> High Discount | O11: =TEXT(Table1[[#This Row],[Date]],"mmm") -> Jan | P11: =Table1[[#This Row],[OrderID]]&" "&Table1[[#This Row],[SalesPerson]] -> O010 Priya
A12: O011 | B12: 2026-01-11 | C12: North | D12: Asha | E12: Tablet | F12: Electronics | G12: 3 | H12: 30000 | I12: 10 | J12: Credit Card | L12: =Table1[[#This Row],[Units]]*Table1[[#This Row],[UnitPrice]]*(1-Table1[[#This Row],[Discount%]]/100) -> 81000 | M12: =IF(L12>50000,"High Value Order","") -> High Value Order | N12: {=_xlfn.IFS(Table1[[#This Row],[Discount%]]>10,"High Discount",Table1[[#This Row],[Discount%]]>5,"Medium Discount",Table1[[#This Row],[Discount%]]<=5,"Low Discount")} -> Medium Discount | O12: =TEXT(Table1[[#This Row],[Date]],"mmm") -> Jan | P12: =Table1[[#This Row],[OrderID]]&" "&Table1[[#This Row],[SalesPerson]] -> O011 Asha
A13: O012 | B13: 2026-01-12 | C13: South | D13: Rahul | E13: Keyboard | F13: Electronics | G13: 5 | H13: 1500 | I13: 0 | J13: Cash | L13: =Table1[[#This Row],[Units]]*Table1[[#This Row],[UnitPrice]]*(1-Table1[[#This Row],[Discount%]]/100) -> 7500 | M13: =IF(L13>50000,"High Value Order","") | N13: {=_xlfn.IFS(Table1[[#This Row],[Discount%]]>10,"High Discount",Table1[[#This Row],[Discount%]]>5,"Medium Discount",Table1[[#This Row],[Discount%]]<=5,"Low Discount")} -> Low Discount | O13: =TEXT(Table1[[#This Row],[Date]],"mmm") -> Jan | P13: =Table1[[#This Row],[OrderID]]&" "&Table1[[#This Row],[SalesPerson]] -> O012 Rahul
... A101: O100 | B101: 2026-04-10 | C101: Central | D101: Priya | E101: Phone | F101: Electronics | G101: 2 | H101: 20000 | I101: 5 | J101: UPI | L101: =Table1[[#This Row],[Units]]*Table1[[#This Row],[UnitPrice]]*(1-Table1[[#This Row],[Discount%]]/100) -> 38000 | M101: =IF(L101>50000,"High Value Order","") | N101: {=_xlfn.IFS(Table1[[#This Row],[Discount%]]>10,"High Discount",Table1[[#This Row],[Discount%]]>5,"Medium Discount",Table1[[#This Row],[Discount%]]<=5,"Low Discount")} -> Low Discount | O101: =TEXT(Table1[[#This Row],[Date]],"mmm") -> Apr | P101: =Table1[[#This Row],[OrderID]]&" "&Table1[[#This Row],[SalesPerson]] -> O100 Priya

Sheet Questions
A1: Questions | B1: Answers
A2: 1. Create a Total Sales column = Units * UnitPrice * (1-Discount%) | B2: DONE | D2: ANS2 | G2: ANS4
A3: 2. Find total revenue by each SalesPerson using SUMIF | B3: DONE | D3: {=_xlfn.UNIQUE(Month!D:D)} -> SalesPerson | G3: {=_xlfn.UNIQUE(Month!C:C)} -> Region
A4: 3. Count number of orders per Region using COUNTIF | B4: DONE | D4: Asha | E4: =SUMIF(Month!D:D,"Asha",Month!L:L) -> 998250 | G4: North | H4: =AVERAGEIF(Month!C:C,Questions!G4,Month!G:G) -> 3.6
A5: 4. Use COUNTIFS to find Rahul's orders in South region | B5: =COUNTIFS(Month!D:D,"Rahul",Month!C:C,"South") -> 20 | D5: Rahul | E5: =SUMIF(Month!D:D,"Rahul",Month!L:L) -> 939000 | G5: South | H5: =AVERAGEIF(Month!C:C,Questions!G5,Month!G:G) -> 3.3
A6: 5. Find total sales from UPI payments | B6: =SUMIF(Month!J:J,"UPI",Month!L:L) -> 1404675 | D6: Neha | E6: =SUMIF(Month!D:D,"Neha",Month!L:L) -> 1178650 | G6: East | H6: =AVERAGEIF(Month!C:C,Questions!G6,Month!G:G) -> 3.1
A7: 6. Identify High Value orders (>50000) | B7: DONE | D7: Vikram | E7: =SUMIF(Month!D:D,"Vikram",Month!L:L) -> 928000 | G7: West | H7: =AVERAGEIF(Month!C:C,Questions!G7,Month!G:G) -> 3.9
A8: 7. Use IFS to categorize Discount as Low/Medium/High | B8: DONE | D8: Priya | E8: =SUMIF(Month!D:D,"Priya",Month!L:L) -> 883700 | G8: Central
A9: 8. Find total sales of Laptop category | B9: =SUMIF(Month!E:E,"Laptop",Month!L:L) -> 2002500 | D9: 0 | G9: 0
A10: 9. Find average Units sold per Region using AVERAGEIF | B10: DONE
A11: 10. Count orders where Units > 5 and Region = East | B11: =COUNTIFS(Month!G:G,">5",Month!C:C,"East") -> 1
A12: 11. Extract month from Date column | B12: Done | D12: ANS3 | G12: ANS18
A13: 12. Find most frequently used PaymentMode | B13: {=INDEX(Table1[PaymentMode],MODE(MATCH(Table1[PaymentMode],Table1[PaymentMode],0)))} -> UPI | D13: {=_xlfn.UNIQUE(Month!C:C)} -> Region | G13: {=_xlfn.UNIQUE(Month!E:E)} -> Product
A14: 13. Use TEXT function to format Date as Day name | B14: Done | D14: North | E14: =COUNTIF(Month!C:C,Questions!D14) -> 20 | G14: Laptop | H14: =_xlfn.XLOOKUP(G14,Month!E:E,Month!H:H,"",0) -> 50000
A15: 14. Create a helper column combining OrderID & SalesPerson | B15: Done | D15: South | E15: =COUNTIF(Month!C:C,Questions!D15) -> 20 | G15: Phone | H15: =_xlfn.XLOOKUP(G15,Month!E:E,Month!H:H,"",0) -> 20000
A16: 15. Find max single order value | B16: =MAX(Month!L:L) -> 200000 | D16: East | E16: =COUNTIF(Month!C:C,Questions!D16) -> 20 | G16: Tablet | H16: =_xlfn.XLOOKUP(G16,Month!E:E,Month!H:H,"",0) -> 30000
A17: 16. Find min UnitPrice product sold | B17: =MIN(Month!H:H) -> 1500 | D17: West | E17: =COUNTIF(Month!C:C,Questions!D17) -> 20 | G17: Headphones | H17: =_xlfn.XLOOKUP(G17,Month!E:E,Month!H:H,"",0) -> 2000
A18: 17. Count how many times each Product appears | B18: Done | D18: Central | G18: Keyboard | H18: =_xlfn.XLOOKUP(G18,Month!E:E,Month!H:H,"",0) -> 1500
A19: 18. Use XLOOKUP/VLOOKUP to fetch UnitPrice by Product | B19: Done | D19: 0 | G19: 0
A20: 19. Find total orders in March 2026 | B20: =COUNTIF(Month!O:O,"Mar") -> 31
A21: 20. Build a summary pivot (Region vs Sales) | B21: Done | D21: ANS16
D22: {=_xlfn.UNIQUE(Month!E:E)} -> Product
D23: Laptop | E23: =COUNTIF(Table1[Product],D23) -> 23
A24: Row Labels | B24: Sum of Units | C24: Sum of UnitPrice | D24: Phone | E24: =COUNTIF(Table1[Product],D24) -> 22
A25: Central | B25: 78 | C25: 383500 | D25: Tablet | E25: =COUNTIF(Table1[Product],D25) -> 22
A26: East | B26: 62 | C26: 530500 | D26: Headphones | E26: =COUNTIF(Table1[Product],D26) -> 16
A27: North | B27: 72 | C27: 460500 | D27: Keyboard | E27: =COUNTIF(Table1[Product],D27) -> 17
A28: South | B28: 66 | C28: 490500 | D28: 0
A29: West | B29: 78 | C29: 442500
A30: Grand Total | B30: 356 | C30: 2307500
