Workbook

Sheet Data
A1: OrderID | B1: OrderDate | C1: CustomerName | D1: Region | E1: Category | F1: Product | G1: Quantity | H1: UnitPrice | I1: TotalAmount | J1: PaymentMethod
A2: ORD1001 | B2: 45772 | C2: Aarav Rao | D2: East | E2: Stationery | F2: Gel Pen Set | G2: 3 | H2: 3721.89 | I2: =G2*H2 -> 11165.67 | J2: Cash on Delivery
A3: ORD1002 | B3: 45747 | C3: Pari Reddy | D3: North | E3: Electronics | F3: Wireless Mouse | G3: 4 | H3: 1278.41 | I3: =G3*H3 -> 5113.64 | J3: Cash on Delivery
A4: ORD1003 | B4: 45685 | C4: Riya Singh | D4: Central | E4: Apparel | F4: Denim Jacket | G4: 8 | H4: 3007.94 | I4: =G4*H4 -> 24063.52 | J4: Credit Card
A5: ORD1004 | B5: 45821 | C5: Aadhya Patel | D5: East | E5: Stationery | F5: Gel Pen Set | G5: 6 | H5: 645.72 | I5: =G5*H5 -> 3874.32 | J5: Net Banking
A6: ORD1005 | B6: 45757 | C6: Diya Joshi | D6: East | E6: Grocery | F6: Olive Oil 1L | G6: 1 | H6: 3689.2 | I6: =G6*H6 -> 3689.2 | J6: Cash on Delivery
A7: ORD1006 | B7: 45785 | C7: Saanvi Verma | D7: Central | E7: Home | F7: Photo Frame | G7: 6 | H7: 2950.16 | I7: =G7*H7 -> 17700.96 | J7: Credit Card
A8: ORD1007 | B8: 45704 | C8: Ayaan Mehta | D8: East | E8: Electronics | F8: Bluetooth Speaker | G8: 2 | H8: 1993.61 | I8: =G8*H8 -> 3987.22 | J8: Net Banking
A9: ORD1008 | B9: 46031 | C9: Sai Patel | D9: East | E9: Stationery | F9: Sticky Notes | G9: 2 | H9: 3104.29 | I9: =G9*H9 -> 6208.58 | J9: Debit Card
A10: ORD1009 | B10: 45908 | C10: Sai Nair | D10: West | E10: Home | F10: Photo Frame | G10: 4 | H10: 3470.38 | I10: =G10*H10 -> 13881.52 | J10: Credit Card
A11: ORD1010 | B11: 45892 | C11: Vivaan Mehta | D11: East | E11: Apparel | F11: Running Shoes | G11: 2 | H11: 1173.27 | I11: =G11*H11 -> 2346.54 | J11: Cash on Delivery
A12: ORD1011 | B12: 45980 | C12: Reyansh Malhotra | D12: West | E12: Apparel | F12: Wool Socks | G12: 3 | H12: 1434.67 | I12: =G12*H12 -> 4304.01 | J12: Debit Card
A13: ORD1012 | B13: 45927 | C13: Pari Reddy | D13: Central | E13: Apparel | F13: Running Shoes | G13: 4 | H13: 4987.03 | I13: =G13*H13 -> 19948.12 | J13: Debit Card
... A121: ORD1120 | B121: 46201 | C121: Aadhya Chopra | D121: South | E121: Stationery | F121: Gel Pen Set | G121: 2 | H121: 3106.04 | I121: =G121*H121 -> 6212.08 | J121: Net Banking

Sheet Formula_Practice
A1: # | B1: Question | C1: Your Formula / Answer
A2: 1 | B2: Find the total sales amount (TotalAmount) across all orders. | C2: =SUM(Data!I:I) -> 1740779.3
A3: 2 | B3: Find the total quantity sold for the 'Electronics' category using SUMIF. | C3: =SUMIF(Data!E:E,"Electronics",Data!G:G) -> 151
A4: 3 | B4: Find the total sales amount for the 'North' region using SUMIF. | C4: =SUMIF(Data!D:D,"North",Data!I:I) -> 319750.43
A5: 4 | B5: Count how many orders were paid using 'UPI' using COUNTIF. | C5: =COUNTIF(Data!J:J,"UPI") -> 16
A6: 5 | B6: Find the total sales amount for orders where Region = 'South' AND Category = 'Apparel' using SUMIFS. | C6: =SUMIFS(Data!I:I,Data!D:D,"South",Data!E:E,"Apparel") -> 67721.18
A7: 6 | B7: Count orders where Quantity is greater than 5 AND PaymentMethod is 'Credit Card' using COUNTIFS. | C7: =COUNTIFS(Data!G:G,">5",Data!J:J,"Credit Card") -> 11
A8: 7 | B8: Find the average UnitPrice of products in the 'Grocery' category using AVERAGEIF. | C8: =AVERAGEIF(Data!E:E,"Grocery",Data!H:H) -> 2454.6565
A9: 8 | B9: Find the CustomerName for OrderID 'ORD1050' using XLOOKUP. | C9: =_xlfn.XLOOKUP("ORD1050",Data!A:A,Data!C:C,"",0,) -> Diya Rao
A10: 9 | B10: Find the TotalAmount for OrderID 'ORD1075' using INDEX and MATCH. | C10: =INDEX(Data!A1:J121,MATCH("ORD1075",Data!A:A,0),9) -> 21369.6
A11: 10 | B11: Find the highest TotalAmount in the entire dataset using MAX. | C11: =MAX(Data!I:I) -> 49516.5
A12: 11 | B12: Find the OrderID with the highest TotalAmount using INDEX/MATCH with MAX. | C12: =INDEX(Data!A1:J121,MATCH(MAX(Data!I:I),Data!I:I,0),1) -> ORD1092
A13: 12 | B13: Find the number of unique Categories in the dataset using SUMPRODUCT and COUNTIF (or UNIQUE + COUNTA). | C13: =COUNTA(_xlfn.UNIQUE(Data!E:E)) -> 7
A14: 13 | B14: List all unique Region values using the UNIQUE function. | C14: ans | D14: {=_xlfn.UNIQUE(Data!D:D)} -> Region
A15: 14 | B15: Create a formula that returns 'High' if TotalAmount > 5000, else 'Low', for the first order (use IF). | C15: =IF(Data!I2>5000,"High","Low") -> High | D15: East
A16: 15 | B16: Find the total sales amount for orders placed after 1 June 2025 using SUMIFS with a date condition. | C16: =SUMIFS(Data!I:I,Data!B:B,">="&DATE(2025,6,1)) -> 1289808.1 | D16: North
A17: 16 | B17: Rank the TotalAmount of the first order among all orders using RANK.EQ. | C17: =_xlfn.RANK.EQ(Data!I2,Data!I:I,1) -> 57 | D17: Central
A18: 17 | B18: Extract the month name from the OrderDate of the first order using TEXT. | C18: =TEXT(Data!B2,"mmmm") -> April | D18: West
A19: 18 | B19: Find the second highest TotalAmount in the dataset using LARGE. | C19: =LARGE(Data!I:I,2) -> 40266.7 | D19: South
A20: 19 | B20: Count how many distinct Products were sold using COUNTIFS or SUMPRODUCT with 1/COUNTIF. | C20: {=SUMPRODUCT(1/COUNTIF(Data!F2:F121,Data!F2:F121))} -> 25 | D20: 0
A21: 20 | B21: Write a LAMBDA formula named DISCOUNTED that takes a price and returns price minus 10% discount, then use it on the first UnitPrice. | C21: NA
B23: Note: All questions refer to the 'Data' sheet (range A2:J121).
